RTk/GPIO.py
RTk/__init__.py
RTk/adaptors.py
RTk/findPort.py
RTk/protocol.py
RTk/rtkserial.py
RTk/smbus.py
RTk/rtk/GPIO.py
RTk/rtk/__init__.py
RTk/rtk/neo.py
RTk/rtk/ports_unix.py
RTk/rtk/ports_win32.py
RTk/rtk/portscan.py
RTk-0.3.14.dist-info/DESCRIPTION.rst
RTk-0.3.14.dist-info/METADATA
RTk-0.3.14.dist-info/RECORD
RTk-0.3.14.dist-info/WHEEL
RTk-0.3.14.dist-info/metadata.json
RTk-0.3.14.dist-info/top_level.txt
