Metadata-Version: 2.0
Name: RTk
Version: 0.3.14
Summary: RTk.GPIO Python Library
Home-page: https://bitbucket.org/ryanteckltd/rtk-gpio-python-side/
Author: Ryanteck LTD.
Author-email: Ryan@ryanteck.uk
License: GPLv3
Keywords: Raspberry Pi GPIO RTk GPIO
Platform: UNKNOWN
Classifier: Development Status :: 4 - Beta
Classifier: Intended Audience :: Developers
Classifier: Intended Audience :: Education
Classifier: Topic :: Education
Classifier: Topic :: System :: Hardware
Classifier: Topic :: Software Development
Classifier: License :: OSI Approved :: GNU General Public License v3 (GPLv3)
Classifier: Programming Language :: Python :: 3
Classifier: Programming Language :: Python :: 3.3
Classifier: Programming Language :: Python :: 3.4
Classifier: Programming Language :: Python :: 3.5
Classifier: Programming Language :: Python :: 3.6
Requires-Dist: future
Requires-Dist: pyserial (>=3)
Requires-Dist: setuptools
Requires-Dist: wheel
Provides-Extra: dev
Requires-Dist: check-manifest; extra == 'dev'
Provides-Extra: test
Requires-Dist: coverage; extra == 'test'
